scenario/__init__.py
scenario/_error_messages.py
scenario/agent_adapter.py
scenario/cache.py
scenario/judge_agent.py
scenario/py.typed
scenario/pytest_plugin.py
scenario/scenario_executor.py
scenario/scenario_state.py
scenario/script.py
scenario/types.py
scenario/user_simulator_agent.py
scenario/_events/__init__.py
scenario/_events/event_alert_message_logger.py
scenario/_events/event_bus.py
scenario/_events/event_reporter.py
scenario/_events/events.py
scenario/_events/messages.py
scenario/_events/utils.py
scenario/_generated/langwatch_api_client/README.md
scenario/_generated/langwatch_api_client/pyproject.toml
scenario/_generated/langwatch_api_client/lang_watch_api_client/__init__.py
scenario/_generated/langwatch_api_client/lang_watch_api_client/client.py
scenario/_generated/langwatch_api_client/lang_watch_api_client/errors.py
scenario/_generated/langwatch_api_client/lang_watch_api_client/py.typed
scenario/_generated/langwatch_api_client/lang_watch_api_client/types.py
scenario/_generated/langwatch_api_client/lang_watch_api_client/api/__init__.py
scenario/_generated/langwatch_api_client/lang_watch_api_client/api/default/__init__.py
scenario/_generated/langwatch_api_client/lang_watch_api_client/api/default/delete_api_annotations_id.py
scenario/_generated/langwatch_api_client/lang_watch_api_client/api/default/delete_api_prompts_by_id.py
scenario/_generated/langwatch_api_client/lang_watch_api_client/api/default/delete_api_scenario_events.py
scenario/_generated/langwatch_api_client/lang_watch_api_client/api/default/get_api_annotations.py
scenario/_generated/langwatch_api_client/lang_watch_api_client/api/default/get_api_annotations_id.py
scenario/_generated/langwatch_api_client/lang_watch_api_client/api/default/get_api_annotations_trace_id.py
scenario/_generated/langwatch_api_client/lang_watch_api_client/api/default/get_api_dataset_by_slug_or_id.py
scenario/_generated/langwatch_api_client/lang_watch_api_client/api/default/get_api_prompts.py
langwatch_scenario-0.7.15.dist-info/METADATA
langwatch_scenario-0.7.15.dist-info/WHEEL
langwatch_scenario-0.7.15.dist-info/entry_points.txt
langwatch_scenario-0.7.15.dist-info/top_level.txt
langwatch_scenario-0.7.15.dist-info/RECORD
