Metadata-Version: 2.4
Name: langwatch-scenario
Version: 0.7.15
Summary: The end-to-end agent testing library
Author-email: LangWatch Team <support@langwatch.ai>
License: MIT
Project-URL: Homepage, https://github.com/langwatch/scenario
Project-URL: Bug Tracker, https://github.com/langwatch/scenario/issues
Classifier: Development Status :: 4 - Beta
Classifier: Intended Audience :: Developers
Classifier: License :: OSI Approved :: MIT License
Classifier: Programming Language :: Python :: 3
Classifier: Programming Language :: Python :: 3.8
Classifier: Programming Language :: Python :: 3.9
Classifier: Programming Language :: Python :: 3.10
Classifier: Programming Language :: Python :: 3.11
Requires-Python: >=3.10
Requires-Dist: pytest>=8.1.1
Requires-Dist: pytest-rerunfailures>=14.0
Requires-Dist: litellm>=1.49.0
Requires-Dist: openai>=1.88.0
Requires-Dist: python-dotenv>=1.0.1
Requires-Dist: termcolor>=2.4.0
Requires-Dist: pydantic>=2.7.0
Requires-Dist: joblib>=1.4.2
Requires-Dist: wrapt>=1.17.2
Requires-Dist: pytest-asyncio>=0.26.0
Requires-Dist: rich<15.0.0,>=13.3.3
Requires-Dist: pksuid>=1.1.2
Requires-Dist: httpx>=0.27.0
Requires-Dist: rx>=3.2.0
Requires-Dist: python-dateutil>=2.9.0.post0
Requires-Dist: pydantic-settings>=2.9.1
Requires-Dist: langwatch>=0.2.19
Requires-Dist: opentelemetry-sdk>=1.20.0
Provides-Extra: dev
Requires-Dist: black; extra == "dev"
Requires-Dist: isort; extra == "dev"
Requires-Dist: pytest-cov; extra == "dev"
Requires-Dist: pre-commit; extra == "dev"
Requires-Dist: pyright; extra == "dev"
Requires-Dist: pydantic-ai; extra == "dev"
Requires-Dist: function-schema; extra == "dev"
Requires-Dist: pdoc3; extra == "dev"
Requires-Dist: respx; extra == "dev"
